<?xml version="1.0" encoding="utf-8" ?>
<dwsync>
<file name="active-bg.gif" server="C:/wamp/www/imobiliaria/" local="130452527751222566" remote="130452527750000000" />
<file name="button_big.gif" server="C:/wamp/www/imobiliaria/" local="130452527751442578" remote="130452527750000000" />
<file name="button_small.gif" server="C:/wamp/www/imobiliaria/" local="130452527751512582" remote="130452527750000000" />
<file name="button_smallest.gif" server="C:/wamp/www/imobiliaria/" local="130452527751892604" remote="130452527750000000" />
<file name="cannot_thumbnail.gif" server="C:/wamp/www/imobiliaria/" local="130452527751952607" remote="130452527750000000" />
<file name="dark-bg.gif" server="C:/wamp/www/imobiliaria/" local="130452527751972609" remote="130452527750000000" />
<file name="down.gif" server="C:/wamp/www/imobiliaria/" local="130452527751992610" remote="130452527750000000" />
<file name="error.gif" server="C:/wamp/www/imobiliaria/" local="130452527752092616" remote="130452527750000000" />
<file name="hover-bg.gif" server="C:/wamp/www/imobiliaria/" local="130452527752112617" remote="130452527750000000" />
<file name="img_not_found.gif" server="C:/wamp/www/imobiliaria/" local="130452527752182621" remote="130452527750000000" />
<file name="menuarrow.gif" server="C:/wamp/www/imobiliaria/" local="130452527752202622" remote="130452527750000000" />
<file name="menuarrow2.gif" server="C:/wamp/www/imobiliaria/" local="130452527752222623" remote="130452527750000000" />
<file name="normal-bg.gif" server="C:/wamp/www/imobiliaria/" local="130452527752242624" remote="130452527750000000" />
<file name="rowhover-bg.gif" server="C:/wamp/www/imobiliaria/" local="130452527752262625" remote="130452527750000000" />
<file name="status-bg.gif" server="C:/wamp/www/imobiliaria/" local="130452527752482638" remote="130452527750000000" />
<file name="title-bg.gif" server="C:/wamp/www/imobiliaria/" local="130452527752502639" remote="130452527750000000" />
<file name="today-bg.gif" server="C:/wamp/www/imobiliaria/" local="130452527752692650" remote="130452527750000000" />
<file name="up.gif" server="C:/wamp/www/imobiliaria/" local="130452527752712651" remote="130452527750000000" />
<file name="warning.gif" server="C:/wamp/www/imobiliaria/" local="130452527752732652" remote="130452527750000000" />
<file name="wdg_down.gif" server="C:/wamp/www/imobiliaria/" local="130452527752752653" remote="130452527750000000" />
<file name="wdg_up.gif" server="C:/wamp/www/imobiliaria/" local="130452527752772654" remote="130452527750000000" />
</dwsync>